djangocms_blog/__init__.py
djangocms_blog/addon.json
djangocms_blog/admin.py
djangocms_blog/apps.py
djangocms_blog/cms_appconfig.py
djangocms_blog/cms_apps.py
djangocms_blog/cms_menus.py
djangocms_blog/cms_plugins.py
djangocms_blog/cms_toolbars.py
djangocms_blog/cms_wizards.py
djangocms_blog/feeds.py
djangocms_blog/fields.py
djangocms_blog/forms.py
djangocms_blog/managers.py
djangocms_blog/models.py
djangocms_blog/settings.py
djangocms_blog/taggit_urls.py
djangocms_blog/urls.py
djangocms_blog/views.py
djangocms_blog/liveblog/__init__.py
djangocms_blog/liveblog/apps.py
djangocms_blog/liveblog/cms_plugins.py
djangocms_blog/liveblog/consumers.py
djangocms_blog/liveblog/models.py
djangocms_blog/liveblog/routing.py
djangocms_blog/liveblog/migrations/0001_initial.py
djangocms_blog/liveblog/migrations/0002_liveblog_title.py
djangocms_blog/liveblog/migrations/0003_auto_20160917_0123.py
djangocms_blog/liveblog/migrations/__init__.py
djangocms_blog/liveblog/static/liveblog/js/liveblog.js
djangocms_blog/liveblog/static/liveblog/js/reconnecting-websocket.min.js
djangocms_blog/liveblog/templates/liveblog/includes/post_detail.html
djangocms_blog/liveblog/templates/liveblog/plugins/liveblog.html
djangocms_blog/locale/ar/LC_MESSAGES/django.mo
djangocms_blog/locale/ar/LC_MESSAGES/django.po
djangocms_blog/locale/de/LC_MESSAGES/django.mo
djangocms_blog/locale/de/LC_MESSAGES/django.po
djangocms_blog/locale/en/LC_MESSAGES/django.mo
djangocms_blog/locale/en/LC_MESSAGES/django.po
djangocms_blog/locale/es/LC_MESSAGES/django.mo
djangocms_blog/locale/es/LC_MESSAGES/django.po
djangocms_blog/locale/et/LC_MESSAGES/django.mo
djangocms_blog/locale/et/LC_MESSAGES/django.po
djangocms_blog/locale/fr/LC_MESSAGES/django.mo
djangocms_blog/locale/fr/LC_MESSAGES/django.po
djangocms_blog/locale/it/LC_MESSAGES/django.mo
djangocms_blog/locale/it/LC_MESSAGES/django.po
djangocms_blog/locale/lt/LC_MESSAGES/django.mo
djangocms_blog/locale/lt/LC_MESSAGES/django.po
djangocms_blog-2.0.9.dist-info/licenses/LICENSE
djangocms_blog-2.0.9.dist-info/METADATA
djangocms_blog-2.0.9.dist-info/WHEEL
djangocms_blog-2.0.9.dist-info/top_level.txt
djangocms_blog-2.0.9.dist-info/RECORD
