Metadata-Version: 2.4
Name: djangocms-blog
Version: 2.0.9
Summary: The blog application for django CMS
Home-page: https://github.com/nephila/djangocms-blog
Author: Iacopo Spalletti
Author-email: i.spalletti@nephila.it
License: BSD
Project-URL: Documentation, https://djangocms-blog.readthedocs.io/
Classifier: License :: OSI Approved :: BSD License
Classifier: Development Status :: 5 - Production/Stable
Classifier: Framework :: Django
Classifier: Framework :: Django :: 3.2
Classifier: Framework :: Django :: 4.1
Classifier: Framework :: Django :: 4.2
Classifier: Programming Language :: Python
Classifier: Programming Language :: Python :: 3
Classifier: Programming Language :: Python :: 3.7
Classifier: Programming Language :: Python :: 3.8
Classifier: Programming Language :: Python :: 3.9
Classifier: Programming Language :: Python :: 3.10
Classifier: Programming Language :: Python :: 3.11
Requires-Python: >=3.7
License-File: LICENSE
Requires-Dist: django-parler>=2.0
Requires-Dist: django-cms<4.0,>=3.9
Requires-Dist: django-taggit>=1.0
Requires-Dist: django-filer>=2.0
Requires-Dist: pytz
Requires-Dist: django-taggit-templatetags
Requires-Dist: django-taggit-autosuggest
Requires-Dist: djangocms-text-ckeditor>=3.9
Requires-Dist: easy-thumbnails>=2.4.1
Requires-Dist: django-meta>=2.4
Requires-Dist: aldryn-apphooks-config>=0.5
Requires-Dist: djangocms-apphook-setup
Requires-Dist: django-sortedm2m
Requires-Dist: lxml
Provides-Extra: taggit-helpers
Requires-Dist: django-taggit-helpers; extra == "taggit-helpers"
Provides-Extra: docs
Requires-Dist: django<5.0; extra == "docs"
Requires-Dist: sphinx<6,>2; extra == "docs"
Requires-Dist: sphinx-rtd-theme; extra == "docs"
Dynamic: license-file
